better_sum/__init__.py
better_sum-0.1.0.dist-info/LICENSE
better_sum-0.1.0.dist-info/METADATA
better_sum-0.1.0.dist-info/WHEEL
better_sum-0.1.0.dist-info/top_level.txt
better_sum-0.1.0.dist-info/RECORD
