Metadata-Version: 2.1
Name: better-sum
Version: 0.1.0
Summary: Python's sum, minus ugly annotations and extra arguments.
Author: pushfoo
License: BSD 2-Clause License
Project-URL: Homepage, https://github.com/pushfoo/python-better-sum
Project-URL: Documentation, https://better-sum.readthedocs.io/en/latest
Project-URL: Issues, https://github.com/pushfoo/python-better-sum/issues
Project-URL: Source, https://github.com/pushfoo/python-better-sum
Classifier: Development Status :: 3 - Alpha
Classifier: Programming Language :: Python :: 3
Classifier: Programming Language :: Python :: 3.9
Classifier: Programming Language :: Python :: 3.10
Classifier: Programming Language :: Python :: 3.11
Classifier: Programming Language :: Python :: 3.12
Classifier: Programming Language :: Python :: 3.13
Classifier: Operating System :: OS Independent
Classifier: Intended Audience :: Developers
Classifier: Topic :: Software Development
Classifier: Topic :: Software Development :: Libraries
Requires-Python: >=3.9
License-File: LICENSE
Requires-Dist: typing-extensions ==4.11.0 ; python_version < "3.11"
Provides-Extra: dev
Requires-Dist: mkdocs ; extra == 'dev'
Requires-Dist: mkdocstrings[python] ; extra == 'dev'
